.gitignore
CHANGELOG.md
LICENSE.txt
MANIFEST.in
README.md
bootstrap.sh
pytest.ini
setup.cfg
setup.py
src/fc/__init__.py
src/fc.disktracker.egg-info/PKG-INFO
src/fc.disktracker.egg-info/SOURCES.txt
src/fc.disktracker.egg-info/dependency_links.txt
src/fc.disktracker.egg-info/entry_points.txt
src/fc.disktracker.egg-info/requires.txt
src/fc.disktracker.egg-info/top_level.txt
src/fc/disktracker/__init__.py
src/fc/disktracker/disk.py
src/fc/disktracker/local.py
src/fc/disktracker/main.py
src/fc/disktracker/snipeit.py
src/fc/disktracker/tests/__init__.py
src/fc/disktracker/tests/conftest.py
src/fc/disktracker/tests/test_disk.py
src/fc/disktracker/tests/test_local.py
src/fc/disktracker/tests/test_main.py
src/fc/disktracker/tests/test_snipeit.py
src/fc/disktracker/tests/etc/disktracker/disktracker.conf
src/fc/disktracker/tests/etc/disktracker/token
src/fc/disktracker/tests/fixtures/smartctl/smartctl_--scan.json
src/fc/disktracker/tests/fixtures/smartctl/smartctl_-i__dev_bus_0_-d_megaraid,0.json
src/fc/disktracker/tests/fixtures/smartctl/smartctl_-i__dev_bus_0_-d_megaraid,1.json
src/fc/disktracker/tests/fixtures/smartctl/smartctl_-i__dev_bus_0_-d_megaraid,2.json
src/fc/disktracker/tests/fixtures/smartctl/smartctl_-i__dev_bus_0_-d_megaraid,3.json
src/fc/disktracker/tests/fixtures/smartctl/smartctl_-i__dev_bus_0_-d_megaraid,4.json
src/fc/disktracker/tests/fixtures/smartctl/smartctl_-i__dev_bus_0_-d_megaraid,5.json
src/fc/disktracker/tests/fixtures/smartctl/smartctl_-i__dev_bus_0_-d_megaraid,6.json
src/fc/disktracker/tests/fixtures/smartctl/smartctl_-i__dev_bus_0_-d_megaraid,7.json
src/fc/disktracker/tests/fixtures/smartctl/smartctl_-i__dev_sda_-d_scsi.json
src/fc/disktracker/tests/fixtures/smartctl/smartctl_-i__dev_sdb_-d_scsi.json
src/fc/disktracker/tests/fixtures/smartctl/smartctl_-i_megaraid,0_-d__dev_bus_0.json
src/fc/disktracker/tests/fixtures/test_snipe_inventory_check_in_one_disk/01_request_statuslabels__get.json
src/fc/disktracker/tests/fixtures/test_snipe_inventory_check_in_one_disk/02_request_models__get.json
src/fc/disktracker/tests/fixtures/test_snipe_inventory_check_in_one_disk/03_request_manufacturers__get.json
